{"brands": [
 {"name": "Two Maids & A Mop", "fields": {
  "liquidCapitalMin": {"value": 61440, "source": "https://www.entrepreneur.com/franchises/directory/two-maids/334414", "year": 2026, "confidence": "medium", "note": "CONFLICT: $61,440 (Entrepreneur) vs $20K (VettedBiz)"},
  "totalInvestmentMin": {"value": 93440, "source": "https://www.franchisedirect.com/two-maids-franchise-costs-fees-fdd", "year": 2025, "confidence": "high", "note": "CONFLICT: PeerSense cites $124K-$193K for claimed 2026 FDD"},
  "totalInvestmentMax": {"value": 149890, "source": "https://www.franchisedirect.com/two-maids-franchise-costs-fees-fdd", "year": 2025, "confidence": "high"},
  "franchiseFee": {"value": 19950, "source": "https://www.franchisedirect.com/two-maids-franchise-costs-fees-fdd", "year": 2025, "confidence": "high", "note": "PLUS separate $40,000 territory fee — true initial fees $59,950"},
  "royaltyPercent": {"value": 7, "source": "https://franchisedecisionradar.com/two-maids-vs-cleaning-authority.html", "year": 2025, "confidence": "high", "note": "TIERED marginal: 7% first $30K/mo declining to 4% above $90K/mo; min $500-1,500/mo"},
  "adFundPercent": {"value": 2, "source": "https://www.franchisedirect.com/two-maids-franchise-costs-fees-fdd", "year": 2025, "confidence": "high", "note": "+franchisor-directed local advertising ~$2,500-3,000/mo"},
  "avgUnitRevenue": {"value": 568172, "source": "https://www.vettedbiz.com/franchises/two-maids/", "year": 2025, "confidence": "medium", "note": "Most commonly cited AUV; quintile data exists (top quintile $1.17M)"},
  "item19Available": {"value": true, "source": "https://franchisedecisionradar.com/two-maids-vs-cleaning-authority.html", "year": 2025, "confidence": "medium", "note": "Disputed by one source; weight of evidence says quintile-based Item 19 exists"},
  "fddAvailable": {"value": true, "source": "https://fddexchange.com/view-fdd-docs/two-maids-2025-fdd-franchise-information-costs-and-fees/", "year": 2025, "confidence": "high"},
  "sbaApproved": {"value": true, "source": "https://peersense.com/franchise/two-maids-and-a-mop", "year": 2026, "confidence": "medium", "note": "SBA loan history, ~1.5% default rate; directory discontinued 2023"},
  "veteranDiscount": {"value": true, "source": "https://www.entrepreneur.com/franchises/directory/two-maids/334414", "year": 2026, "confidence": "high", "note": "15% off franchise + territory fees, veterans and spouses"},
  "multiUnitAvailable": {"value": true, "source": "https://franchisedecisionradar.com/two-maids-vs-cleaning-authority.html", "year": 2025, "confidence": "medium"},
  "exclusiveTerritories": {"value": true, "source": "https://www.franchisepayback.com/franchise/two-maids", "year": 2024, "confidence": "high", "note": "Protected by ZIP codes, min 50,000 households; national-account carve-outs"},
  "ownerTypes": {"value": ["owner_operator", "semi_absentee"], "source": "https://www.entrepreneur.com/franchises/directory/two-maids/334414", "year": 2026, "confidence": "medium"},
  "canRunFromHome": {"value": false, "source": "https://www.entrepreneur.com/franchises/directory/two-maids/334414", "year": 2026, "confidence": "medium", "note": "Commercial office required"},
  "canRunPartTime": {"value": false, "source": "https://www.entrepreneur.com/franchises/directory/two-maids/334414", "year": 2026, "confidence": "high"},
  "absenteeOwnership": {"value": true, "source": "https://www.entrepreneur.com/franchises/directory/two-maids/334414", "year": 2026, "confidence": "medium", "note": "Listed allowed; treat as semi-absentee in practice"},
  "trainingWeeks": {"value": 2, "source": "https://www.franchisedirect.com/two-maids-franchise-costs-fees-fdd", "year": 2025, "confidence": "high", "note": "10 days in Alabama"},
  "ongoingSupport": {"value": ["initial 10-day classroom + OJT training", "ongoing operations coaching", "proprietary technology platform ($650/mo)", "ServiceMaster Brands infrastructure"], "source": "https://www.franchisedirect.com/two-maids-franchise-costs-fees-fdd", "year": 2025, "confidence": "medium", "note": "ServiceMaster Brands acquired 2021"},
  "marketingSupport": {"value": ["2% national brand fund", "franchisor-directed local advertising ($2,500-3,000/mo)"], "source": "https://franchisedecisionradar.com/two-maids-vs-cleaning-authority.html", "year": 2025, "confidence": "medium"},
  "employeesRequired": {"value": "2+ to start (cleaning teams of 2)", "source": "https://www.entrepreneur.com/franchises/directory/two-maids/334414", "year": 2026, "confidence": "medium"},
  "totalUnits": {"value": 165, "source": "https://www.entrepreneur.com/franchises/directory/two-maids/334414", "year": 2026, "confidence": "medium", "note": "144 franchised YE2024 per FDD-based sources; all franchised"},
  "yearFounded": {"value": 2003, "source": "https://www.franchisedirect.com/two-maids-franchise-costs-fees-fdd", "year": 2025, "confidence": "high"},
  "yearFranchising": {"value": 2013, "source": "https://www.franchisedirect.com/two-maids-franchise-costs-fees-fdd", "year": 2025, "confidence": "high"},
  "closureCount": {"value": null, "source": "unverified", "note": "Net +7/+19/+26 through 2024"},
  "isGrowing": {"value": true, "source": "https://franchisedecisionradar.com/two-maids-vs-cleaning-authority.html", "year": 2025, "confidence": "high", "note": "+55.7% 3-yr growth"}
 }, "notes": "Headline fee understates true initial fees ($19,950 + $40,000 territory = $59,950). Tiered 7%→4% royalty. Investment range conflict between FDD years flagged."},
 {"name": "HomeVestors of America", "fields": {
  "liquidCapitalMin": {"value": 120000, "source": "https://www.entrepreneur.com/franchises/directory/homevestors-of-america/282436", "year": 2026, "confidence": "medium"},
  "totalInvestmentMin": {"value": 107500, "source": "https://www.entrepreneur.com/franchises/directory/homevestors-of-america/282436", "year": 2026, "confidence": "medium", "note": "CONFLICT: $150K (FC 2026) / $155K (SharpSheets); low end = Associate tier"},
  "totalInvestmentMax": {"value": 477250, "source": "https://www.franchisechatter.com/2026/04/25/homevestors-franchise-review-2026-costs-fees-news-average-revenues-and-or-profits/", "year": 2025, "confidence": "high"},
  "franchiseFee": {"value": 85000, "source": "https://www.franchisechatter.com/2026/04/25/homevestors-franchise-review-2026-costs-fees-news-average-revenues-and-or-profits/", "year": 2025, "confidence": "high", "note": "$42,500 Associate tier / $85,000 Full"},
  "royaltyPercent": {"value": null, "source": "unverified", "note": "NO revenue royalty: tiered TRANSACTION fees 0.8%-3.0% of each property's sales price + $399/mo flat"},
  "adFundPercent": {"value": null, "source": "unverified", "note": "Not %-based: $300 per transaction (capped) + mandatory local We Buy Ugly Houses ad spend $1,000-5,000/mo; system avg ad spend $72,573 (2024)"},
  "avgUnitRevenue": {"value": null, "source": "unverified", "note": "Item 19's $616,948 'average' is GROSS PRICE DIFFERENTIAL (resale minus purchase prices), NOT revenue — excludes rehab/holding/selling costs; median $344,550; heavily skewed — excluded as misleading for AUV comparisons"},
  "item19Available": {"value": true, "source": "https://www.franchisechatter.com/2026/04/25/homevestors-franchise-review-2026-costs-fees-news-average-revenues-and-or-profits/", "year": 2025, "confidence": "high", "note": "Discloses gross price differential + ad spend, 898 franchises, quartiles"},
  "fddAvailable": {"value": true, "source": "https://www.franchisedirect.com/realestatefranchises/homevestors-of-america-franchise-08785/ufoc/", "year": 2025, "confidence": "high"},
  "sbaApproved": {"value": null, "source": "unverified", "note": "RE investing generally ineligible for SBA 7(a)"},
  "veteranDiscount": {"value": true, "source": "https://www.entrepreneur.com/franchises/directory/homevestors-of-america/282436", "year": 2026, "confidence": "medium", "note": "10% off fee"},
  "multiUnitAvailable": {"value": null, "source": "unverified", "note": "Per-market license model (Associate vs Full tiers)"},
  "exclusiveTerritories": {"value": false, "source": "https://www.entrepreneur.com/franchises/directory/homevestors-of-america/282436", "year": 2026, "confidence": "medium", "note": "Shared advertising markets"},
  "ownerTypes": {"value": ["owner_operator", "semi_absentee"], "source": "https://www.entrepreneur.com/franchises/directory/homevestors-of-america/282436", "year": 2026, "confidence": "medium"},
  "canRunFromHome": {"value": true, "source": "https://www.entrepreneur.com/franchises/directory/homevestors-of-america/282436", "year": 2026, "confidence": "high"},
  "canRunPartTime": {"value": true, "source": "https://www.entrepreneur.com/franchises/directory/homevestors-of-america/282436", "year": 2026, "confidence": "high", "note": "Many Associate franchisees start part-time"},
  "absenteeOwnership": {"value": false, "source": "https://www.entrepreneur.com/franchises/directory/homevestors-of-america/282436", "year": 2026, "confidence": "high"},
  "trainingWeeks": {"value": 1, "source": "https://www.entrepreneur.com/franchises/directory/homevestors-of-america/282436", "year": 2026, "confidence": "medium", "note": "~52 hrs initial + Development Agent mentoring"},
  "ongoingSupport": {"value": ["Development Agent (mentor) coaching per ad market", "ValueChek valuation software", "lead generation via national We Buy Ugly Houses brand", "transaction support and financing relationships"], "source": "https://www.franchisechatter.com/2026/04/25/homevestors-franchise-review-2026-costs-fees-news-average-revenues-and-or-profits/", "year": 2025, "confidence": "medium"},
  "marketingSupport": {"value": ["national We Buy Ugly Houses advertising", "pooled local ad-market media buying", "per-transaction marketing fund"], "source": "https://www.franchisechatter.com/2026/04/25/homevestors-franchise-review-2026-costs-fees-news-average-revenues-and-or-profits/", "year": 2025, "confidence": "medium"},
  "employeesRequired": {"value": "1 (can operate solo)", "source": "https://www.entrepreneur.com/franchises/directory/homevestors-of-america/282436", "year": 2026, "confidence": "medium"},
  "minFootprint": {"value": "None — home-based permitted", "source": "https://www.entrepreneur.com/franchises/directory/homevestors-of-america/282436", "year": 2026, "confidence": "medium"},
  "totalUnits": {"value": 1003, "source": "https://www.franchisechatter.com/2026/04/25/homevestors-franchise-review-2026-costs-fees-news-average-revenues-and-or-profits/", "year": 2024, "confidence": "high", "note": "981 franchised + 22 company YE2024"},
  "yearFounded": {"value": 1996, "source": "https://www.entrepreneur.com/franchises/directory/homevestors-of-america/282436", "year": 2026, "confidence": "high"},
  "yearFranchising": {"value": 1996, "source": "https://www.entrepreneur.com/franchises/directory/homevestors-of-america/282436", "year": 2026, "confidence": "high"},
  "closureCount": {"value": 101, "source": "https://www.franchisechatter.com/2026/04/25/homevestors-franchise-review-2026-costs-fees-news-average-revenues-and-or-profits/", "year": 2024, "confidence": "high", "note": "Net franchised decline 1,082→981 in 2024; -173 over 2022-24"},
  "isGrowing": {"value": false, "source": "https://www.entrepreneur.com/franchises/directory/homevestors-of-america/282436", "year": 2026, "confidence": "high", "note": "-15%; shrinking 3 straight years"}
 }, "notes": "MODEL ANOMALY: real-estate INVESTING franchise — no revenue royalty; per-transaction fees (0.8-3.0% of property price) + $399/mo. Item 19 figure is gross price differential NOT revenue (excluded from AUV). System contracting (-101 units 2024). Diligence flags: 2025-26 press incl. franchisee guilty plea + ProPublica scrutiny of elderly-seller tactics."},
 {"name": "Freeway Insurance", "fields": {
  "liquidCapitalMin": {"value": 50000, "source": "https://sharpsheets.io/blog/freeway-insurance-franchise-fdd-profits-costs/", "year": 2025, "confidence": "medium", "note": "CONFLICT: $50K (SharpSheets) vs $10K (VettedBiz)"},
  "totalInvestmentMin": {"value": 34950, "source": "https://www.entrepreneur.com/franchises/directory/freeway-insurance/336590", "year": 2025, "confidence": "high"},
  "totalInvestmentMax": {"value": 84000, "source": "https://www.entrepreneur.com/franchises/directory/freeway-insurance/336590", "year": 2025, "confidence": "high"},
  "franchiseFee": {"value": 25000, "source": "https://www.franchisepayback.com/franchise/freeway-insurance", "year": 2024, "confidence": "medium", "note": "$10K-$25K range by program/market"},
  "royaltyPercent": {"value": 14, "source": "https://sharpsheets.io/blog/freeway-insurance-franchise-fdd-profits-costs/", "year": 2025, "confidence": "high", "note": "14% of COMMISSIONS (agency model) + $650/mo tech fee"},
  "adFundPercent": {"value": 7, "source": "https://sharpsheets.io/blog/freeway-insurance-franchise-fdd-profits-costs/", "year": 2025, "confidence": "high", "note": "Combined 21% fee load on commission revenue — high vs industry"},
  "avgUnitRevenue": {"value": 121000, "source": "https://www.franchisepayback.com/franchise/freeway-insurance", "year": 2024, "confidence": "medium", "note": "AUV = COMMISSION revenue not premiums; VettedBiz cites $133,896 (newer FDD); tiny franchised cohort (19 units)"},
  "item19Available": {"value": true, "source": "https://sharpsheets.io/blog/freeway-insurance-franchise-fdd-profits-costs/", "year": 2025, "confidence": "medium", "note": "Thin sample: only 19 franchised units in 2024"},
  "fddAvailable": {"value": true, "source": "https://www.freefddlibrary.com/franchises/freeway-insurancer", "year": 2025, "confidence": "medium"},
  "sbaApproved": {"value": null, "source": "unverified", "note": "In-house financing offered"},
  "veteranDiscount": {"value": true, "source": "https://www.entrepreneur.com/franchises/directory/freeway-insurance/336590", "year": 2025, "confidence": "medium", "note": "$10,000 off fee"},
  "multiUnitAvailable": {"value": null, "source": "unverified", "note": "Program too new/small"},
  "exclusiveTerritories": {"value": false, "source": "https://www.entrepreneur.com/franchises/directory/freeway-insurance/336590", "year": 2025, "confidence": "medium", "note": "Limited Protected Area, not true exclusivity"},
  "ownerTypes": {"value": ["owner_operator"], "source": "https://www.entrepreneur.com/franchises/directory/freeway-insurance/336590", "year": 2025, "confidence": "medium"},
  "canRunFromHome": {"value": false, "source": "https://www.entrepreneur.com/franchises/directory/freeway-insurance/336590", "year": 2025, "confidence": "high", "note": "Walk-in retail storefront"},
  "canRunPartTime": {"value": false, "source": "https://www.entrepreneur.com/franchises/directory/freeway-insurance/336590", "year": 2025, "confidence": "high"},
  "absenteeOwnership": {"value": false, "source": "https://www.entrepreneur.com/franchises/directory/freeway-insurance/336590", "year": 2025, "confidence": "high"},
  "trainingWeeks": {"value": 3, "source": "https://www.entrepreneur.com/franchises/directory/freeway-insurance/336590", "year": 2025, "confidence": "medium", "note": "77h classroom + 40h OJT; insurance licensing separate"},
  "ongoingSupport": {"value": ["carrier appointments through Confie network", "management/operations training", "technology platform ($650/mo)", "up to 4 annual training events"], "source": "https://www.franchisepayback.com/franchise/freeway-insurance", "year": 2024, "confidence": "medium"},
  "marketingSupport": {"value": ["7% national brand marketing fund", "national Freeway brand advertising (Hispanic/non-standard auto focus)"], "source": "https://sharpsheets.io/blog/freeway-insurance-franchise-fdd-profits-costs/", "year": 2025, "confidence": "medium"},
  "employeesRequired": {"value": "1-2", "source": "https://www.entrepreneur.com/franchises/directory/freeway-insurance/336590", "year": 2025, "confidence": "medium"},
  "totalUnits": {"value": 615, "source": "https://www.entrepreneur.com/franchises/directory/freeway-insurance/336590", "year": 2026, "confidence": "medium", "note": "ANOMALY: only ~19 FRANCHISED vs ~543 company-owned (2024 FDD) — overwhelmingly corporate system"},
  "yearFounded": {"value": 1987, "source": "https://www.entrepreneur.com/franchises/directory/freeway-insurance/336590", "year": 2025, "confidence": "high", "note": "Parent: Confie"},
  "yearFranchising": {"value": 2021, "source": "https://www.entrepreneur.com/franchises/directory/freeway-insurance/336590", "year": 2025, "confidence": "high"},
  "closureCount": {"value": null, "source": "unverified"},
  "isGrowing": {"value": true, "source": "https://www.entrepreneur.com/franchises/directory/freeway-insurance/336590", "year": 2026, "confidence": "medium", "note": "+31% but growth largely corporate-unit expansion"},
  "geographicFocus": {"value": "32 states incl. CA, TX, FL, IL (system-wide incl. corporate)", "source": "https://www.franchisepayback.com/franchise/freeway-insurance", "year": 2024, "confidence": "medium"}
 }, "notes": "AGENCY ANOMALY: AUV = commission income (~$121-134K), not premiums. 21% combined fee load. Nearly all-corporate system (19 franchised vs 543 corporate) — thin franchise data. Insurance licensing required."}
]}
